LICENSE
MANIFEST.in
README.rst
setup.py
pydpi/__init__.py
pydpi/dispatch.py
pydpi/utils.py
pydpi/src/bridge/ies/pydpi_bridge.c
pydpi/templates/pydpi_gen_common.sv.tmpl
pydpi/templates/pydpi_gen_func_{func_name}.sv.tmpl
pydpi/templates/pydpi_gen_funcs_{mod_name}.py.tmpl
pydpi/templates/pydpi_gen_mod_{mod_name}.sv.tmpl
pydpi/templates/pydpi_gen_params.sv.tmpl
pydpi/templates/pydpi_gen_registration.py.tmpl
python_svlog.egg-info/PKG-INFO
python_svlog.egg-info/SOURCES.txt
python_svlog.egg-info/dependency_links.txt
python_svlog.egg-info/entry_points.txt
python_svlog.egg-info/requires.txt
python_svlog.egg-info/top_level.txt